ueml/__init__.py
ueml/ueml.py
UEML-0.7.dist-info/METADATA
UEML-0.7.dist-info/WHEEL
UEML-0.7.dist-info/top_level.txt
UEML-0.7.dist-info/RECORD
