Metadata-Version: 2.2
Name: UEML
Version: 0.7
Summary: Official UEML Parser
Home-page: https://github.com/juanvel4000/ueml
Author: juanvel400
Author-email: juanvel400@proton.me
Classifier: Programming Language :: Python :: 3
Classifier: License :: OSI Approved :: MIT License
Classifier: Operating System :: OS Independent
Requires-Python: >=3.6
Dynamic: author
Dynamic: author-email
Dynamic: classifier
Dynamic: home-page
Dynamic: requires-python
Dynamic: summary
